tickr_agent/__init__.py
tickr_agent/data_sources.py
tickr_agent/main.py
tickr_agent/pandas_utils.py
tickr_agent/prompt.py
tickr_agent-0.1.0.dist-info/LICENSE
tickr_agent-0.1.0.dist-info/METADATA
tickr_agent-0.1.0.dist-info/WHEEL
tickr_agent-0.1.0.dist-info/RECORD
