Metadata-Version: 2.1
Name: tickr-agent
Version: 0.1.0
Summary: Tickr Agent - Swarms -- TGCS
Home-page: https://github.com/The-Swarm-Corporation/TickrAgent
License: MIT
Keywords: artificial intelligence,deep learning,optimizers,Prompt Engineering
Author: Kye Gomez
Author-email: kye@apac.ai
Requires-Python: >=3.10,<4.0
Classifier: Development Status :: 4 - Beta
Classifier: Intended Audience :: Developers
Classifier: License :: OSI Approved :: MIT License
Classifier: Programming Language :: Python :: 3
Classifier: Programming Language :: Python :: 3.10
Classifier: Programming Language :: Python :: 3.11
Classifier: Programming Language :: Python :: 3.12
Classifier: Programming Language :: Python :: 3.9
Classifier: Topic :: Scientific/Engineering :: Artificial Intelligence
Requires-Dist: ffn
Requires-Dist: loguru
Requires-Dist: pydantic
Requires-Dist: swarms
Requires-Dist: yfinance
Project-URL: Documentation, https://github.com/The-Swarm-Corporation/TickrAgent
Project-URL: Repository, https://github.com/The-Swarm-Corporation/TickrAgent
